turbo_helper/__init__.py
turbo_helper/apps.py
turbo_helper/channels/__init__.py
turbo_helper/channels/broadcasts.py
turbo_helper/channels/stream_name.py
turbo_helper/channels/streams_channel.py
turbo_helper/constants.py
turbo_helper/middleware.py
turbo_helper/renderers.py
turbo_helper/response.py
turbo_helper/shortcuts.py
turbo_helper/signals.py
turbo_helper/stream.py
turbo_helper/templatetags/__init__.py
turbo_helper/templatetags/turbo_helper.py
turbo_helper/turbo_power.py
django_turbo_helper-2.1.5.dist-info/METADATA
django_turbo_helper-2.1.5.dist-info/WHEEL
django_turbo_helper-2.1.5.dist-info/licenses/LICENSE
django_turbo_helper-2.1.5.dist-info/RECORD
