Metadata-Version: 2.4
Name: django-turbo-helper
Version: 2.1.5
Summary: Hotwire/Turbo helpers for Django, inspired by Rails.
License: MIT
License-File: LICENSE
Author: Michael Yin
Author-email: michaelyin@accordbox.com
Requires-Python: >=3.10
Classifier: License :: OSI Approved :: MIT License
Classifier: Programming Language :: Python :: 3
Classifier: Programming Language :: Python :: 3.10
Classifier: Programming Language :: Python :: 3.11
Classifier: Programming Language :: Python :: 3.12
Classifier: Programming Language :: Python :: 3.13
Classifier: Programming Language :: Python :: 3.14
Requires-Dist: django (>=5.2)
Requires-Dist: django-actioncable (>=1.0.4)
Requires-Dist: django-template-simplify (>=1.0.2)
Project-URL: Changelog, https://github.com/rails-inspire-django/django-turbo-helper/releases
Project-URL: Homepage, https://github.com/rails-inspire-django/django-turbo-helper
